Metadata-Version: 2.4
Name: git-surgeon
Version: 0.1.0
Summary: Git subcommand for change-centric workflows.
Author-email: konfou <mail@konfou.xyz>
License-Expression: MIT
Project-URL: Homepage, https://github.com/konfou/git-surgeon
Project-URL: Issues, https://github.com/konfou/git-surgeon/issues
Requires-Python: >=3.10
License-File: LICENSE
Dynamic: license-file
